pytest_nhsd_apim/__init__.py
pytest_nhsd_apim/apigee_apis.py
pytest_nhsd_apim/apigee_edge.py
pytest_nhsd_apim/auth_journey.py
pytest_nhsd_apim/config.py
pytest_nhsd_apim/identity_service.py
pytest_nhsd_apim/log.py
pytest_nhsd_apim/nhsd_apim_authorization.py
pytest_nhsd_apim/pytest_nhsd_apim.py
pytest_nhsd_apim/secrets.py
pytest_nhsd_apim/token_cache.py
pytest_nhsd_apim-6.0.6.dist-info/METADATA
pytest_nhsd_apim-6.0.6.dist-info/WHEEL
pytest_nhsd_apim-6.0.6.dist-info/entry_points.txt
pytest_nhsd_apim-6.0.6.dist-info/top_level.txt
pytest_nhsd_apim-6.0.6.dist-info/RECORD
