Metadata-Version: 2.4
Name: pytest-nhsd-apim
Version: 6.0.6
Summary: Pytest plugin accessing NHSDigital's APIM proxies
Home-page: https://github.com/NHSDigital/pytest-nhsd-apim
Author: Adrian Ciobanita
Author-email: adrian.ciobanita1@nhs.net
Maintainer: Alex Carrie
Maintainer-email: alexander.carrie1@nhs.net
License: MIT
Classifier: Framework :: Pytest
Requires-Python: >=3.10
Requires-Dist: Authlib<2.0.0,>=1.6.6
Requires-Dist: cryptography>44.0.1
Requires-Dist: lxml<6.0.0,>=5.3.1
Requires-Dist: pycryptodome<4.0.0,>=3.20.0
Requires-Dist: PyJWT<3.0.0,>=2.8.0
Requires-Dist: pyotp<3.0.0,>=2.9.0
Requires-Dist: pytest<9.0.0,>=8.2.0
Requires-Dist: requests<3.0.0,>=2.32.0
Requires-Dist: toml<1.0.0,>=0.10.2
Requires-Dist: typing-extensions<5.0.0,>=4.12.2
Requires-Dist: pydantic<3.0.0,>=2.9.2
Requires-Dist: wheel<0.47.0,>=0.46.2
Requires-Dist: pydantic-settings<3.0.0,>=2.2.1
Requires-Dist: setuptools<81.0.0,>=80.0.1
Requires-Dist: urllib3<3.0.0,>=2.6.3
Dynamic: author
Dynamic: author-email
Dynamic: classifier
Dynamic: description
Dynamic: description-content-type
Dynamic: home-page
Dynamic: license
Dynamic: maintainer
Dynamic: maintainer-email
Dynamic: requires-dist
Dynamic: requires-python
Dynamic: summary
